fifo_sync.v
module fifo_sync # (
    parameter depth = 16 ,
    parameter data_width = 8,
    parameter address_width = 4

    )(  input   wire clk,
        input wire reset,
        input wire wr_ena,
        input wire rd_ena,
        input wire [data_width-1:0] d_in,
        output reg [data_width-1:0] d_out,
        output wire empty,
        output wire full
    );
    // memory array for fifo
    reg [data_width-1:0]memory[0:depth-1];

    //write pointer declaration
    reg [address_width:0] wr_ptr;

    //read pointer declaration
    reg[address_width:0]rd_ptr;

    //count logic
    reg[address_width:0] count;

    //write logic
    always@(posedge clk or negedge reset) begin
        if(~reset)begin
            wr_ptr <= 0;
        end
        else begin
            if(wr_ena && !full)begin
                memory[wr_ptr[address_width-1:0]] <= d_in;
                wr_ptr <= wr_ptr +1;
            end
        end
    end

    //read logic
    always@(posedge clk or negedge reset)begin
        if(~reset)begin
            rd_ptr <= 0;
        end
        else begin
            if(rd_ena && !empty)begin
                d_out <= memory[rd_ptr[address_width-1:0]];
                rd_ptr <= rd_ptr +1;
            end
        end
    end

    // count logic
    always@(posedge clk or negedge reset)begin
        if(~reset)begin
            count <= 0;
        end

        else begin 
            case({wr_ena && !full , rd_ena && !empty}) 
                2'b10: count <= count+1;
                2'b01: count <= count-1;
                default: count <= count;
        
            endcase
        end
    end

    assign empty = (count ==0);
    assign full = (count == depth);

endmodule

fifo_sync_tb.v
module fifo_sync_tb;
    parameter depth =16;
    parameter data_width = 8;
    parameter address_width = 4;

    reg clk;
    reg reset;
    reg wr_ena;
    reg rd_ena;
    reg [data_width-1:0]d_in;
    wire [data_width-1:0]d_out;
    wire full;
    wire empty;

    fifo_sync #(
        .depth(depth),
        .data_width(data_width),
        .address_width(address_width)
    ) dut (
        .clk(clk),
        .reset(reset),
        .wr_ena(wr_ena),
        .rd_ena(rd_ena),
        .d_in(d_in),
        .d_out(d_out),
        .empty(empty),
        .full(full)
    );

    // Clock generation
    initial clk = 0;
    always #5 clk = ~clk;

    // Reset task
    task apply_reset;
    begin
        reset = 0;
        wr_ena = 0;
        rd_ena = 0;
        d_in   = 0;
        #20;
        reset = 1;
        $display("RESET APPLIED");
    end
    endtask

    // Write task
    task fifo_write(input [data_width-1:0] data);
    begin
        @(posedge clk);
        if (!full) begin
            wr_ena = 1;
            rd_ena = 0;
            d_in   = data;
            $display("WRITE: %h", data);
        end else begin
            $display("WRITE BLOCKED (FIFO FULL)");
        end
    end
    endtask

    // Read task
    task fifo_read;
    begin
        @(posedge clk);
        if (!empty) begin
            rd_ena = 1;
            wr_ena = 0;
            $display("READ issued");
        end else begin
            $display("READ BLOCKED (FIFO EMPTY)");
        end
    end
    endtask

// Simultaneous read/write task
    task fifo_read_write(input [data_width-1:0] data);
    begin
        @(posedge clk);
        if (!full && !empty) begin
            wr_ena = 1;
            rd_ena = 1;
            d_in   = data;
            $display("SIMULTANEOUS R/W: write=%h", data);
        end
    end
    endtask

 // Idle task
    task fifo_idle;
    begin
        @(posedge clk);
        wr_ena = 0;
        rd_ena = 0;
    end
    endtask

    initial begin
        $dumpfile("fifo.vcd");
        $dumpvars(0, fifo_sync_tb);

        apply_reset;

        // Condition 1: Write only
        fifo_write(8'h11);
        fifo_write(8'h22);
        fifo_write(8'h33);
        fifo_idle;

        // Condition 2: Read only
        fifo_read;
        fifo_read;
        fifo_idle;

        // Condition 3: Simultaneous read & write
        fifo_read_write(8'h44);
        fifo_read_write(8'h55);
        fifo_idle;

        // Condition 4: Read until empty
        repeat (5) fifo_read;
        fifo_idle;

        // Condition 5: Write until full
        repeat (depth + 2) fifo_write(d_in + 8'h11);
        fifo_idle;

        #20;
        $finish;
    end

endmodule

fifo.vcd
$date
	Thu Feb 26 23:55:51 2026
$end
$version
	Icarus Verilog
$end
$timescale
	1s
$end
$scope module fifo_sync_tb $end
$var wire 8 ! d_out [7:0] $end
$var wire 1 " empty $end
$var wire 1 # full $end
$var reg 1 $ clk $end
$var reg 8 % d_in [7:0] $end
$var reg 1 & rd_ena $end
$var reg 1 ' reset $end
$var reg 1 ( wr_ena $end
$scope module dut $end
$var wire 1 ) clk $end
$var wire 8 * d_in [7:0] $end
$var wire 1 " empty $end
$var wire 1 # full $end
$var wire 1 + rd_ena $end
$var wire 1 , reset $end
$var wire 1 - wr_ena $end
$var reg 5 . count [4:0] $end
$var reg 8 / d_out [7:0] $end
$var reg 5 0 rd_ptr [4:0] $end
$var reg 5 1 wr_ptr [4:0] $end
$upscope $end
$scope task apply_reset $end
$upscope $end
$scope task fifo_idle $end
$upscope $end
$scope task fifo_read $end
$upscope $end
$scope task fifo_read_write $end
$var reg 8 2 data [7:0] $end
$upscope $end
$scope task fifo_write $end
$var reg 8 3 data [7:0] $end
$upscope $end
$upscope $end
$enddefinitions $end
#0
$dumpvars
bx 3
bx 2
b0 1
b0 0
bx /
b0 .
0-
0,
0+
b0 *
0)
0(
0'
0&
b0 %
0$
0#
1"
bx !
$end
#5
1$
1)
#10
0$
0)
#15
1$
1)
#20
0$
0)
b10001 3
1'
1,
#25
b1 .
0"
b1 1
b100010 3
b10001 %
b10001 *
1(
1-
1$
1)
#30
0$
0)
#35
b10 1
b10 .
b110011 3
b100010 %
b100010 *
1$
1)
#40
0$
0)
#45
b11 .
b11 1
b110011 %
b110011 *
1$
1)
#50
0$
0)
#55
0(
0-
1$
1)
#60
0$
0)
#65
b10 .
b1 0
b10001 /
b10001 !
1&
1+
1$
1)
#70
0$
0)
#75
b10 0
b100010 /
b100010 !
b1 .
1$
1)
#80
0$
0)
#85
b1000100 2
0&
0+
1$
1)
#90
0$
0)
#95
b100 1
b11 0
b110011 /
b110011 !
b1010101 2
b1000100 %
b1000100 *
1&
1+
1(
1-
1$
1)
#100
0$
0)
#105
b100 0
b1000100 /
b1000100 !
b101 1
b1010101 %
b1010101 *
1$
1)
#110
0$
0)
#115
0&
0+
0(
0-
1$
1)
#120
0$
0)
#125
b0 .
1"
b101 0
b1010101 /
b1010101 !
1&
1+
1$
1)
#130
0$
0)
#135
1$
1)
#140
0$
0)
#145
1$
1)
#150
0$
0)
#155
1$
1)
#160
0$
0)
#165
1$
1)
#170
0$
0)
#175
b1100110 3
0&
0+
1$
1)
#180
0$
0)
#185
b1 .
0"
b110 1
b1110111 3
b1100110 %
b1100110 *
1(
1-
1$
1)
#190
0$
0)
#195
b111 1
b10 .
b10001000 3
b1110111 %
b1110111 *
1$
1)
#200
0$
0)
#205
b11 .
b1000 1
b10011001 3
b10001000 %
b10001000 *
1$
1)
#210
0$
0)
#215
b1001 1
b100 .
b10101010 3
b10011001 %
b10011001 *
1$
1)
#220
0$
0)
#225
b101 .
b1010 1
b10111011 3
b10101010 %
b10101010 *
1$
1)
#230
0$
0)
#235
b1011 1
b110 .
b11001100 3
b10111011 %
b10111011 *
1$
1)
#240
0$
0)
#245
b111 .
b1100 1
b11011101 3
b11001100 %
b11001100 *
1$
1)
#250
0$
0)
#255
b1101 1
b1000 .
b11101110 3
b11011101 %
b11011101 *
1$
1)
#260
0$
0)
#265
b1001 .
b1110 1
b11111111 3
b11101110 %
b11101110 *
1$
1)
#270
0$
0)
#275
b1111 1
b1010 .
b10000 3
b11111111 %
b11111111 *
1$
1)
#280
0$
0)
#285
b1011 .
b10000 1
b100001 3
b10000 %
b10000 *
1$
1)
#290
0$
0)
#295
b10001 1
b1100 .
b110010 3
b100001 %
b100001 *
1$
1)
#300
0$
0)
#305
b1101 .
b10010 1
b1000011 3
b110010 %
b110010 *
1$
1)
#310
0$
0)
#315
b10011 1
b1110 .
b1010100 3
b1000011 %
b1000011 *
1$
1)
#320
0$
0)
#325
b1111 .
b10100 1
b1100101 3
b1010100 %
b1010100 *
1$
1)
#330
0$
0)
#335
b10101 1
b10000 .
1#
b1110110 3
b1100101 %
b1100101 *
1$
1)
#340
0$
0)
#345
1$
1)
#350
0$
0)
#355
1$
1)
#360
0$
0)
#365
0(
0-
1$
1)
